{"blocks":[{"macPrefix":"4865EE00","companyName":"DefPower Ltd","maskLength":28},{"macPrefix":"4865EE10","companyName":"Gopod Group Limited","maskLength":28},{"macPrefix":"4865EE20","companyName":"CaptionCall","maskLength":28},{"macPrefix":"4865EE30","companyName":"Data Technology Inc.","maskLength":28},{"macPrefix":"4865EE40","companyName":"Mission Microwave Technologies, Inc","maskLength":28},{"macPrefix":"4865EE50","companyName":"Swistec Systems AG","maskLength":28},{"macPrefix":"4865EE60","companyName":"shenzhen sunflower technologies CO., LIMITED","maskLength":28},{"macPrefix":"4865EE70","companyName":"Venture Research Inc.","maskLength":28},{"macPrefix":"4865EE80","companyName":"SmartDisplayer Technology Co., Ltd.","maskLength":28},{"macPrefix":"4865EE90","companyName":"VideoStitch, Inc","maskLength":28},{"macPrefix":"4865EEA0","companyName":"Shenzhen Inpor cloud Computing Co., Ltd.","maskLength":28},{"macPrefix":"4865EEB0","companyName":"EnBW Energie Baden-Württemberg AG","maskLength":28},{"macPrefix":"4865EEC0","companyName":"Dnv Gl","maskLength":28},{"macPrefix":"4865EED0","companyName":"Winn Technology Co.,Ltd","maskLength":28},{"macPrefix":"4865EEE0","companyName":"Cnu","maskLength":28}]}