{"blocks":[{"macPrefix":"8C557000","companyName":"AST International GmbH","maskLength":28},{"macPrefix":"8C557010","companyName":"LLC Katusha Print","maskLength":28},{"macPrefix":"8C557020","companyName":"Microvision Inc","maskLength":28},{"macPrefix":"8C557030","companyName":"ScandiNova Systems","maskLength":28},{"macPrefix":"8C557040","companyName":"Next Vision Tech(Ningbo)Co.,LTD","maskLength":28},{"macPrefix":"8C557050","companyName":"Private","maskLength":28},{"macPrefix":"8C557060","companyName":"Joule Group Limites","maskLength":28},{"macPrefix":"8C557070","companyName":"Eideal Company Limited","maskLength":28},{"macPrefix":"8C557080","companyName":"Nayax LTD","maskLength":28},{"macPrefix":"8C557090","companyName":"Neptronic Ltd","maskLength":28},{"macPrefix":"8C5570A0","companyName":"Fortune Brands Innovations, Inc.","maskLength":28},{"macPrefix":"8C5570B0","companyName":"Sernet (Suzhou) Technologies Corporation","maskLength":28},{"macPrefix":"8C5570C0","companyName":"Antronix Inc.,","maskLength":28},{"macPrefix":"8C5570D0","companyName":"EPSa Elektronik \u0026 Präzisionsbau Saalfeld GmbH","maskLength":28},{"macPrefix":"8C5570E0","companyName":"Johnson Health Tech. (Shanghai) Co.,Ltd.","maskLength":28}]}