{"blocks":[{"macPrefix":"7CBACC00","companyName":"TGT Limited","maskLength":28},{"macPrefix":"7CBACC10","companyName":"Changsha SUNYE Electric Co., Ltd.","maskLength":28},{"macPrefix":"7CBACC20","companyName":"Maco Lighting Pty. Ltd.","maskLength":28},{"macPrefix":"7CBACC30","companyName":"Izkare","maskLength":28},{"macPrefix":"7CBACC40","companyName":"Sun Asia Trade Co.","maskLength":28},{"macPrefix":"7CBACC50","companyName":"Fortem Technologies, Inc.","maskLength":28},{"macPrefix":"7CBACC60","companyName":"Fossil Power Systems Inc","maskLength":28},{"macPrefix":"7CBACC70","companyName":"Virgin Orbit","maskLength":28},{"macPrefix":"7CBACC80","companyName":"Collinear Networks Inc.","maskLength":28},{"macPrefix":"7CBACC90","companyName":"Yongguan Electronic Technology (D.G)LTD","maskLength":28},{"macPrefix":"7CBACCA0","companyName":"Annapurna labs","maskLength":28},{"macPrefix":"7CBACCB0","companyName":"Briowireless Inc.","maskLength":28},{"macPrefix":"7CBACCC0","companyName":"Flying Loft Inc.","maskLength":28},{"macPrefix":"7CBACCD0","companyName":"SIGMA-ELEKTRO GmbH","maskLength":28},{"macPrefix":"7CBACCE0","companyName":"Alpha Technologies, Llc","maskLength":28}]}