{"blocks":[{"macPrefix":"ECA7B100","companyName":"Nanjing Xinyun Technology Co., Ltd","maskLength":28},{"macPrefix":"ECA7B110","companyName":"AKOM Technologies Private Limited","maskLength":28},{"macPrefix":"ECA7B120","companyName":"Annapurna labs","maskLength":28},{"macPrefix":"ECA7B130","companyName":"Strongbyte Solutions Limited","maskLength":28},{"macPrefix":"ECA7B140","companyName":"Sichuan Ruiting Zhihui Technology Co., Ltd","maskLength":28},{"macPrefix":"ECA7B150","companyName":"Chicony Power Technology (Dongguan) Co,. Ltd.","maskLength":28},{"macPrefix":"ECA7B160","companyName":"Digital Audio Labs","maskLength":28},{"macPrefix":"ECA7B170","companyName":"Shenzhen Lanroot Technology Co., Ltd","maskLength":28},{"macPrefix":"ECA7B180","companyName":"Shenzhen zhst video technology co.,ltd","maskLength":28},{"macPrefix":"ECA7B190","companyName":"Print International Limited","maskLength":28},{"macPrefix":"ECA7B1A0","companyName":"Annapurna labs","maskLength":28},{"macPrefix":"ECA7B1B0","companyName":"Shenzhen Adreamer Elite Co.,Ltd","maskLength":28},{"macPrefix":"ECA7B1C0","companyName":"Hiromokuten Co.,Ltd.","maskLength":28},{"macPrefix":"ECA7B1D0","companyName":"Usu Telecom India Private Limited","maskLength":28},{"macPrefix":"ECA7B1E0","companyName":"Artisight, Inc.","maskLength":28}]}